CHANGES
LICENSE
MANIFEST.in
README.rst
setup.py
swigibpy.py
swigify_ib.i
IB/API_VersionNum.txt
IB/swig_wrap.cpp
IB/swig_wrap.h
IB/PosixSocketClient/EClientSocketBase.cpp
IB/PosixSocketClient/EPosixClientSocket.cpp
IB/PosixSocketClient/EPosixClientSocket.h
IB/PosixSocketClient/EPosixClientSocketPlatform.h
IB/Shared/CommissionReport.h
IB/Shared/CommonDefs.h
IB/Shared/Contract.h
IB/Shared/EClient.h
IB/Shared/EClientSocketBase.h
IB/Shared/EClientSocketBaseImpl.h
IB/Shared/EWrapper.h
IB/Shared/Execution.h
IB/Shared/HScrollListBox.cpp
IB/Shared/HScrollListBox.h
IB/Shared/IBString.h
IB/Shared/Order.h
IB/Shared/OrderState.h
IB/Shared/ScannerSubscription.h
IB/Shared/StdAfx.h
IB/Shared/TagValue.h
IB/Shared/TwsSocketClientErrors.h
IB/Shared/shared_ptr.h
examples/contractdetails.py
examples/customerror.py
examples/historicaldata.py
examples/placeorder.py
patches/gcc_4_7
patches/mfc_msc_mixup
patches/shared_ptr_bool_conv
swigibpy.egg-info/PKG-INFO
swigibpy.egg-info/SOURCES.txt
swigibpy.egg-info/dependency_links.txt
swigibpy.egg-info/top_level.txt