Metadata-Version: 1.1
Name: swigibpy
Version: 0.4
Summary: Third party Python API for Interactive Brokers
Home-page: https://github.com/Komnomnomnom/swigibpy/
Author: Kieran O'Mahony
Author-email: kieranom@gmail.com
License: New BSD License
Keywords: interactive brokers,tws
Platform: UNKNOWN
Classifier: Programming Language :: Python
Classifier: Programming Language :: Python :: 2
Classifier: Programming Language :: Python :: 3
Classifier: Development Status :: 4 - Beta
Classifier: Environment :: Other Environment
Classifier: Intended Audience :: Developers
Classifier: License :: OSI Approved :: BSD License
Classifier: Operating System :: OS Independent
Classifier: Topic :: Software Development :: Libraries :: Python Modules
Classifier: Topic :: Office/Business :: Financial
